atomic_execution_control/__init__.py
atomic_execution_control/atomic_execution_control.py
atomic_execution_control-0.1.5.dist-info/LICENSE
atomic_execution_control-0.1.5.dist-info/METADATA
atomic_execution_control-0.1.5.dist-info/WHEEL
atomic_execution_control-0.1.5.dist-info/top_level.txt
atomic_execution_control-0.1.5.dist-info/RECORD
