Metadata-Version: 2.1
Name: atomic-execution-control
Version: 0.1.5
Summary: Ensures atomic executions across AWS services using DynamoDB to prevent race conditions in distributed applications.
Home-page: https://github.com/jdaarevalo/atomic_execution_control
Author: Jose David Arevalo
Author-email: jdaarevalo@gmail.com
Keywords: atomic execution,DynamoDB,AWS Lambda,AWS Fargate,EC2,distributed systems,concurrency control,race condition prevention,cloud computing,AWS services,state management
Classifier: Programming Language :: Python :: 3
Classifier: License :: OSI Approved :: MIT License
Classifier: Operating System :: OS Independent
Requires-Python: >=3.6
License-File: LICENSE
Requires-Dist: boto3 >=1.14.0
